copick/__init__.py
copick/models.py
copick/cli/__init__.py
copick/cli/add.py
copick/cli/browse.py
copick/cli/cli.py
copick/cli/config.py
copick/cli/cp.py
copick/cli/deposit.py
copick/cli/ext.py
copick/cli/grouped_cli.py
copick/cli/info.py
copick/cli/make_templates.py
copick/cli/mv.py
copick/cli/new.py
copick/cli/rm.py
copick/cli/stats.py
copick/cli/sync.py
copick/cli/util.py
copick/impl/__init__.py
copick/impl/cryoet_data_portal.py
copick/impl/filesystem.py
copick/impl/overlay.py
copick/ops/__init__.py
copick/ops/_markdown.py
copick/ops/add.py
copick/ops/browser.py
copick/ops/deposit.py
copick/ops/get.py
copick/ops/manage.py
copick/ops/open.py
copick/ops/run.py
copick/ops/stats.py
copick/ops/sync.py
copick/util/__init__.py
copick/util/escape.py
copick/util/log.py
copick/util/ome.py
copick/util/path_util.py
copick/util/portal.py
copick/util/relion.py
copick/util/sync.py
copick/util/uri.py
copick-1.17.2.dist-info/METADATA
copick-1.17.2.dist-info/WHEEL
copick-1.17.2.dist-info/entry_points.txt
copick-1.17.2.dist-info/licenses/LICENSE
copick-1.17.2.dist-info/RECORD
