Metadata-Version: 2.4
Name: copick
Version: 1.17.2
Summary: Definitions for a collaborative cryoET annotation tool.
Project-URL: Repository, https://github.com/copick/copick.git
Project-URL: Issues, https://github.com/copick/copick/issues
Project-URL: docs, https://copick.github.io/copick/
Project-URL: documentation, https://copick.github.io/copick/
Author-email: "Utz H. Ermel" <utz.ermel@czii.org>, Jonathan Schwartz <jonathan.schwartz@czii.org>, "Kyle I. S. Harrington" <kyle@kyleharrington.com>
License: MIT License
License-File: LICENSE
Keywords: annotation,collaborative,copick,cryo-et,cryoet,segmentation,tomography
Classifier: Development Status :: 3 - Alpha
Classifier: License :: OSI Approved :: MIT License
Requires-Python: >=3.9
Requires-Dist: click>=8.1.8
Requires-Dist: cryoet-data-portal>=4.4.1
Requires-Dist: distinctipy>=1.3.4
Requires-Dist: fsspec>=2025.5.1
Requires-Dist: mrcfile>=1.5.4
Requires-Dist: numcodecs<0.16.0
Requires-Dist: numpy>=2.0.2
Requires-Dist: ome-zarr>=0.10.2
Requires-Dist: pandas>=2.0.0
Requires-Dist: psutil>=7.0.0
Requires-Dist: pydantic>=2
Requires-Dist: rich>=14.0.0
Requires-Dist: s3fs>=2025.5.1
Requires-Dist: scikit-image>=0.24.0
Requires-Dist: sshfs>=2025.2.0
Requires-Dist: textual>=3.5.0
Requires-Dist: tqdm>=4.67.1
Requires-Dist: trimesh>=4.6.12
Requires-Dist: zarr<3
Provides-Extra: all
Requires-Dist: smbprotocol>=1.15.0; extra == 'all'
Provides-Extra: dev
Requires-Dist: black>=25.1.0; extra == 'dev'
Requires-Dist: ipython>=8.18.1; extra == 'dev'
Requires-Dist: notebook>=7.4.3; extra == 'dev'
Requires-Dist: pre-commit>=4.2.0; extra == 'dev'
Requires-Dist: ruff>=0.12.0; extra == 'dev'
Requires-Dist: textual-dev>=1.7.0; extra == 'dev'
Provides-Extra: docs
Requires-Dist: mkdocs-autorefs>=1.4.2; extra == 'docs'
Requires-Dist: mkdocs-material>=9.6.14; extra == 'docs'
Requires-Dist: mkdocs>=1.6.1; extra == 'docs'
Requires-Dist: mkdocstrings[python]>=0.29.1; extra == 'docs'
Provides-Extra: fledgeling
Requires-Dist: pooch>=1.8.2; extra == 'fledgeling'
Requires-Dist: smbprotocol>=1.15.0; extra == 'fledgeling'
Provides-Extra: smb
Requires-Dist: smbprotocol>=1.15.0; extra == 'smb'
Provides-Extra: test
Requires-Dist: pooch>=1.8.2; extra == 'test'
Requires-Dist: pytest-cov>=6.2.1; extra == 'test'
Requires-Dist: pytest>=8.4.1; extra == 'test'
Requires-Dist: smbprotocol>=1.15.0; extra == 'test'
